salik/__init__.py
salik/portfolio.py
salik-0.2.0.dist-info/LICENSE
salik-0.2.0.dist-info/METADATA
salik-0.2.0.dist-info/WHEEL
salik-0.2.0.dist-info/top_level.txt
salik-0.2.0.dist-info/RECORD
