Metadata-Version: 2.1
Name: salik
Version: 0.2.0
Summary: A Python package to showcase Salik Uddin's professional portfolio
Home-page: https://github.com/salik03/salik
Author: Salik Uddin
Author-email: uddinsalik@outlook.com
Classifier: Programming Language :: Python :: 3
Classifier: License :: OSI Approved :: MIT License
Classifier: Operating System :: OS Independent
Classifier: Intended Audience :: Developers
Classifier: Topic :: Software Development :: Libraries :: Python Modules
Requires-Python: >=3.6
License-File: LICENSE
